{"cameraMode":{"drawMode":0,"name":"Shaded","section":"Shading Mode"},"sceneLighting":true,"audioPlay":false,"sceneViewState":{"m_AlwaysRefresh":false,"showFog":true,"showSkybox":true,"showFlares":true,"showImageEffects":true,"showParticleSystems":true,"showVisualEffectGraphs":true,"m_FxEnabled":true},"in2DMode":false,"pivot":{"x":733.557373046875,"y":427.63360595703127,"z":42.0283203125},"rotation":{"x":-0.08221147954463959,"y":-0.10980106145143509,"z":0.009113561362028122,"w":-0.990506649017334},"size":758.9488525390625,"orthographic":false}